vsrife/IFNet_HDv3_v4_0.py
vsrife/IFNet_HDv3_v4_1.py
vsrife/IFNet_HDv3_v4_10.py
vsrife/IFNet_HDv3_v4_11.py
vsrife/IFNet_HDv3_v4_12.py
vsrife/IFNet_HDv3_v4_12_lite.py
vsrife/IFNet_HDv3_v4_13.py
vsrife/IFNet_HDv3_v4_13_lite.py
vsrife/IFNet_HDv3_v4_14.py
vsrife/IFNet_HDv3_v4_14_lite.py
vsrife/IFNet_HDv3_v4_15.py
vsrife/IFNet_HDv3_v4_15_lite.py
vsrife/IFNet_HDv3_v4_16_lite.py
vsrife/IFNet_HDv3_v4_17.py
vsrife/IFNet_HDv3_v4_17_lite.py
vsrife/IFNet_HDv3_v4_18.py
vsrife/IFNet_HDv3_v4_19.py
vsrife/IFNet_HDv3_v4_2.py
vsrife/IFNet_HDv3_v4_20.py
vsrife/IFNet_HDv3_v4_21.py
vsrife/IFNet_HDv3_v4_22.py
vsrife/IFNet_HDv3_v4_22_lite.py
vsrife/IFNet_HDv3_v4_23.py
vsrife/IFNet_HDv3_v4_24.py
vsrife/IFNet_HDv3_v4_25.py
vsrife/IFNet_HDv3_v4_25_heavy.py
vsrife/IFNet_HDv3_v4_25_lite.py
vsrife/IFNet_HDv3_v4_26.py
vsrife/IFNet_HDv3_v4_26_heavy.py
vsrife/IFNet_HDv3_v4_3.py
vsrife/IFNet_HDv3_v4_4.py
vsrife/IFNet_HDv3_v4_5.py
vsrife/IFNet_HDv3_v4_6.py
vsrife/IFNet_HDv3_v4_7.py
vsrife/IFNet_HDv3_v4_8.py
vsrife/IFNet_HDv3_v4_9.py
vsrife/__init__.py
vsrife/__main__.py
vsrife/warplayer.py
vsrife/models/flownet_v4.0.pkl
vsrife/models/flownet_v4.1.pkl
vsrife/models/flownet_v4.10.pkl
vsrife/models/flownet_v4.11.pkl
vsrife/models/flownet_v4.12.lite.pkl
vsrife/models/flownet_v4.12.pkl
vsrife/models/flownet_v4.13.lite.pkl
vsrife/models/flownet_v4.13.pkl
vsrife/models/flownet_v4.14.lite.pkl
vsrife/models/flownet_v4.14.pkl
vsrife/models/flownet_v4.15.lite.pkl
vsrife/models/flownet_v4.15.pkl
vsrife/models/flownet_v4.16.lite.pkl
vsrife/models/flownet_v4.17.lite.pkl
vsrife/models/flownet_v4.17.pkl
vsrife/models/flownet_v4.18.pkl
vsrife/models/flownet_v4.19.pkl
vsrife/models/flownet_v4.2.pkl
vsrife/models/flownet_v4.20.pkl
vsrife/models/flownet_v4.21.pkl
vsrife/models/flownet_v4.22.lite.pkl
vsrife/models/flownet_v4.22.pkl
vsrife/models/flownet_v4.23.pkl
vsrife/models/flownet_v4.24.pkl
vsrife/models/flownet_v4.25.heavy.pkl
vsrife/models/flownet_v4.25.lite.pkl
vsrife/models/flownet_v4.25.pkl
vsrife-5.6.0.dist-info/METADATA
vsrife-5.6.0.dist-info/WHEEL
vsrife-5.6.0.dist-info/licenses/LICENSE
vsrife-5.6.0.dist-info/RECORD
