Metadata-Version: 2.4
Name: vsrife
Version: 5.6.0
Summary: RIFE function for VapourSynth
Project-URL: Homepage, https://github.com/HolyWu/vs-rife
Project-URL: Issues, https://github.com/HolyWu/vs-rife/issues
Author-email: HolyWu <holywu@gmail.com>
License-File: LICENSE
Keywords: PyTorch,RIFE,TensorRT,VapourSynth
Classifier: Environment :: GPU :: NVIDIA CUDA
Classifier: License :: OSI Approved :: MIT License
Classifier: Operating System :: OS Independent
Classifier: Programming Language :: Python :: 3
Classifier: Topic :: Multimedia :: Video
Requires-Python: >=3.10
Requires-Dist: numpy
Requires-Dist: requests
Requires-Dist: torch>=2.6.0
Requires-Dist: tqdm
Requires-Dist: vapoursynth>=66
